pygav/__init__.py
pygav/data.py
pygav/utils.py
pygav-0.2.3.dist-info/LICENSE
pygav-0.2.3.dist-info/METADATA
pygav-0.2.3.dist-info/WHEEL
pygav-0.2.3.dist-info/top_level.txt
pygav-0.2.3.dist-info/RECORD
