Metadata-Version: 2.1
Name: pygav
Version: 0.2.3
Summary: Useful stuff
Author: Nikos Gavalas
License: DO WHAT THE FUCK YOU WANT TO PUBLIC LICENSE
Project-URL: Homepage, https://github.com/nikosgavalas/pygav
Keywords: utilities
Classifier: Programming Language :: Python
Classifier: Programming Language :: Python :: 3
Requires-Python: >=3.8
License-File: LICENSE
Requires-Dist: pandas <3,>=2.0.2
Requires-Dist: matplotlib <4,>=3.7.1
Requires-Dist: seaborn <1,>=0.12.2
Provides-Extra: dev
Requires-Dist: pytest ; extra == 'dev'
Requires-Dist: pytest-cov ; extra == 'dev'
